docstringer/__init__.py
docstringer/decorators.py
docstringer/events.py
docstringer/formatters.py
docstringer-0.1.1.dist-info/LICENSE
docstringer-0.1.1.dist-info/WHEEL
docstringer-0.1.1.dist-info/METADATA
docstringer-0.1.1.dist-info/RECORD
