Metadata-Version: 2.1
Name: docstringer
Version: 0.1.1
Summary: Create documentation of your function call stack from their docstrings 
Home-page: https://github.com/ttamg/docstringer
License: UNKNOWN
Author: Matt Gosden
Author-email: mdgosden@gmail.com
Requires-Python: >=3.6
Classifier: License :: OSI Approved :: MIT License
